keyio/__init__.py
keyio/keyutils.py
keyio/mouseutils.py
keyio/windowutils.py
keyio/lib/keyutils.dll
keyio/lib/mouseutils.dll
keyio/lib/windowutils.dll
keyio-1.0.0.dist-info/LICENSE
keyio-1.0.0.dist-info/METADATA
keyio-1.0.0.dist-info/WHEEL
keyio-1.0.0.dist-info/top_level.txt
keyio-1.0.0.dist-info/RECORD
