Metadata-Version: 2.1
Name: keyio
Version: 1.0.0
Summary: A simple package to manage basic IO operations for mouse, keyboard and windows.
Home-page: https://github.com/keyywind/keyio
Author: Keyywind
Author-email: kevinwater127@gmail.com
Project-URL: Bug Tracker, https://github.com/keyywind/keyio/issues
Classifier: Programming Language :: Python :: 3
Classifier: License :: OSI Approved :: MIT License
Classifier: Operating System :: Microsoft :: Windows :: Windows 10
Requires-Python: >=3.7
License-File: LICENSE
Requires-Dist: markdown
